evalsone/__init__.py
evalsone/client.py
tests/__init__.py
tests/test_client.py
evalsone-0.1.2.dist-info/METADATA
evalsone-0.1.2.dist-info/WHEEL
evalsone-0.1.2.dist-info/top_level.txt
evalsone-0.1.2.dist-info/RECORD
