Metadata-Version: 2.1
Name: evalsone
Version: 0.1.2
Author: EvalsOne
Author-email: contact@evalsone.com
Requires-Python: >=3.9
Requires-Dist: requests>=2.25.1
Requires-Dist: pydantic
